test_release_tool/__init__.py
test_release_tool/main.py
test_release_tool-0.2.0.dist-info/LICENSE.txt
test_release_tool-0.2.0.dist-info/METADATA
test_release_tool-0.2.0.dist-info/WHEEL
test_release_tool-0.2.0.dist-info/entry_points.txt
test_release_tool-0.2.0.dist-info/top_level.txt
test_release_tool-0.2.0.dist-info/RECORD
