Metadata-Version: 2.1
Name: test-release-tool
Version: 0.2.0
Summary: Test for mar10/yabs
Home-page: https://github.com/mar10/test-release-tool
Author: Martin Wendt
Author-email: yabs@wwwendt.de
Maintainer: Martin Wendt
Maintainer-email: yabs@wwwendt.de
License: MIT
Keywords: test,temporary,setup
Platform: UNKNOWN
Classifier: Development Status :: 1 - Planning
Classifier: Environment :: Console
Classifier: Intended Audience :: Developers
Classifier: License :: OSI Approved :: MIT License
Classifier: Operating System :: OS Independent
Classifier: Programming Language :: Python
Classifier: Programming Language :: Python :: 3
Classifier: Programming Language :: Python :: 3.5
Classifier: Programming Language :: Python :: 3.6
Classifier: Programming Language :: Python :: 3.7
Classifier: Programming Language :: Python :: 3.8
Classifier: Topic :: Software Development :: Testing
